looseserver/__init__.py
looseserver/client/__init__.py
looseserver/client/abstract.py
looseserver/client/flask.py
looseserver/client/http.py
looseserver/client/response.py
looseserver/client/rule.py
looseserver/common/__init__.py
looseserver/common/api.py
looseserver/common/response.py
looseserver/common/rule.py
looseserver/common/utils.py
looseserver/default/__init__.py
looseserver/default/client/__init__.py
looseserver/default/client/flask.py
looseserver/default/client/http.py
looseserver/default/client/response.py
looseserver/default/client/rule.py
looseserver/default/common/__init__.py
looseserver/default/common/configuration.py
looseserver/default/common/constants.py
looseserver/default/server/__init__.py
looseserver/default/server/application.py
looseserver/default/server/response.py
looseserver/default/server/rule.py
looseserver/default/server/run.py
looseserver/server/__init__.py
looseserver/server/api.py
looseserver/server/application.py
looseserver/server/core.py
looseserver/server/response.py
looseserver/server/rule.py
loose_server-1.0.0.dist-info/LICENSE
loose_server-1.0.0.dist-info/METADATA
loose_server-1.0.0.dist-info/WHEEL
loose_server-1.0.0.dist-info/top_level.txt
loose_server-1.0.0.dist-info/RECORD
