Metadata-Version: 2.1
Name: loose-server
Version: 1.0.0
Summary: Dynamically configurable server
Home-page: https://github.com/KillAChicken/loose-server
Author: KillAChicken
Author-email: KillAChicken@yandex.ru
License: UNKNOWN
Platform: UNKNOWN
Classifier: License :: OSI Approved :: MIT License
Classifier: Operating System :: OS Independent
Classifier: Programming Language :: Python :: 3
Classifier: Topic :: Software Development :: Testing
Classifier: Topic :: Software Development :: Testing :: Mocking
Requires-Dist: Flask
Requires-Dist: flask-restful
Requires-Dist: requests
